huey/__init__.py
huey/api.py
huey/constants.py
huey/consumer.py
huey/consumer_options.py
huey/exceptions.py
huey/registry.py
huey/serializer.py
huey/signals.py
huey/storage.py
huey/utils.py
huey/bin/__init__.py
huey/bin/huey_consumer.py
huey/contrib/__init__.py
huey/contrib/asyncio.py
huey/contrib/helpers.py
huey/contrib/kyototycoon.py
huey/contrib/mini.py
huey/contrib/sql_huey.py
huey/contrib/djhuey/__init__.py
huey/contrib/djhuey/models.py
huey/contrib/djhuey/management/__init__.py
huey/contrib/djhuey/management/commands/__init__.py
huey/contrib/djhuey/management/commands/run_huey.py
huey/tests/__init__.py
huey/tests/__main__.py
huey/tests/base.py
huey/tests/test_api.py
huey/tests/test_consumer.py
huey/tests/test_crontab.py
huey/tests/test_helpers.py
huey/tests/test_immediate.py
huey/tests/test_kt_huey.py
huey/tests/test_priority.py
huey/tests/test_registry.py
huey/tests/test_serializer.py
huey/tests/test_signals.py
huey/tests/test_sql_huey.py
huey/tests/test_storage.py
huey/tests/test_utils.py
huey/tests/test_wrappers.py
huey-2.5.5.data/scripts/huey_consumer.py
huey-2.5.5.dist-info/LICENSE
huey-2.5.5.dist-info/METADATA
huey-2.5.5.dist-info/WHEEL
huey-2.5.5.dist-info/entry_points.txt
huey-2.5.5.dist-info/top_level.txt
huey-2.5.5.dist-info/RECORD
