Metadata-Version: 2.1
Name: huey
Version: 2.5.5
Summary: huey, a little task queue
Home-page: http://github.com/coleifer/huey/
Author: Charles Leifer
Author-email: coleifer@gmail.com
Project-URL: Documentation, https://huey.readthedocs.io
Project-URL: Changelog, https://github.com/coleifer/huey/blob/master/CHANGELOG.md
Classifier: Development Status :: 5 - Production/Stable
Classifier: Intended Audience :: Developers
Classifier: License :: OSI Approved :: MIT License
Classifier: Operating System :: OS Independent
Classifier: Programming Language :: Python
Classifier: Programming Language :: Python :: 2.7
Classifier: Programming Language :: Python :: 3.4
Classifier: Programming Language :: Python :: 3.5
Classifier: Programming Language :: Python :: 3.6
Classifier: Programming Language :: Python :: 3.7
Classifier: Programming Language :: Python :: 3.8
Classifier: Programming Language :: Python :: 3.9
Classifier: Programming Language :: Python :: 3.10
Classifier: Programming Language :: Python :: 3.11
Classifier: Programming Language :: Python :: 3.12
Classifier: Programming Language :: Python :: 3.13
Classifier: Programming Language :: Python :: 3.14
Classifier: Topic :: Software Development :: Libraries :: Python Modules
Provides-Extra: backends
Provides-Extra: redis
License-File: LICENSE
